inmanta_plugins/dummy_module/__init__.py
inmanta_plugins/dummy_module/setup.cfg
inmanta_plugins/dummy_module/files/.gitkeep
inmanta_plugins/dummy_module/model/_init.cf
inmanta_plugins/dummy_module/templates/.gitkeep
inmanta_module_dummy_module-2.1.0.dist-info/METADATA
inmanta_module_dummy_module-2.1.0.dist-info/WHEEL
inmanta_module_dummy_module-2.1.0.dist-info/top_level.txt
inmanta_module_dummy_module-2.1.0.dist-info/RECORD
