Metadata-Version: 2.1
Name: inmanta-module-dummy-module
Version: 2.1.0
Summary: a dummy module
License: ASL 2.0
Requires-Dist: inmanta-module-std
